gitcommit_ai/__init__.py
gitcommit_ai/action/__init__.py
gitcommit_ai/action/runner.py
gitcommit_ai/action/scorer.py
gitcommit_ai/action/validator.py
gitcommit_ai/cli/__init__.py
gitcommit_ai/cli/main.py
gitcommit_ai/cli/picker.py
gitcommit_ai/cli/setup.py
gitcommit_ai/core/__init__.py
gitcommit_ai/core/config.py
gitcommit_ai/core/diff_parser.py
gitcommit_ai/core/git.py
gitcommit_ai/generator/__init__.py
gitcommit_ai/generator/generator.py
gitcommit_ai/generator/message.py
gitcommit_ai/generator/multi_generator.py
gitcommit_ai/gitmoji/__init__.py
gitcommit_ai/gitmoji/mapper.py
gitcommit_ai/gitmoji/validator.py
gitcommit_ai/hooks/__init__.py
gitcommit_ai/hooks/manager.py
gitcommit_ai/hooks/template.py
gitcommit_ai/prompts/__init__.py
gitcommit_ai/prompts/loader.py
gitcommit_ai/prompts/templates/anthropic.txt
gitcommit_ai/prompts/templates/cohere.txt
gitcommit_ai/prompts/templates/deepseek.txt
gitcommit_ai/prompts/templates/gemini.txt
gitcommit_ai/prompts/templates/mistral.txt
gitcommit_ai/prompts/templates/ollama.txt
gitcommit_ai/prompts/templates/openai.txt
gitcommit_ai/providers/__init__.py
gitcommit_ai/providers/anthropic.py
gitcommit_ai/providers/base.py
gitcommit_ai/providers/cohere.py
gitcommit_ai/providers/deepseek.py
gitcommit_ai/providers/gemini.py
gitcommit_ai/providers/mistral.py
gitcommit_ai/providers/ollama.py
gitcommit_ai/providers/openai.py
gitcommit_ai/providers/registry.py
gitcommit_ai/stats/__init__.py
gitcommit_ai/stats/aggregator.py
gitcommit_ai/stats/database.py
gitcommit_ai/stats/exporter.py
gitcommit_ai-0.1.1.dist-info/METADATA
gitcommit_ai-0.1.1.dist-info/WHEEL
gitcommit_ai-0.1.1.dist-info/entry_points.txt
gitcommit_ai-0.1.1.dist-info/RECORD
