Metadata-Version: 2.4
Name: gitcommit-ai
Version: 0.1.1
Summary: AI-powered git commit message generator with 7 providers, git hooks, and custom prompts
Project-URL: Homepage, https://github.com/gagarinyury/gitcommit-ai
Project-URL: Repository, https://github.com/gagarinyury/gitcommit-ai
Project-URL: Issues, https://github.com/gagarinyury/gitcommit-ai/issues
Project-URL: Documentation, https://github.com/gagarinyury/gitcommit-ai#readme
Author-email: Yury Gagarin <yurcheg13@gmail.com>
License: MIT
Keywords: ai,anthropic,commit,commit-message,conventional-commits,deepseek,git,gitmoji,ollama,openai
Classifier: Development Status :: 4 - Beta
Classifier: Environment :: Console
Classifier: Intended Audience :: Developers
Classifier: License :: OSI Approved :: MIT License
Classifier: Operating System :: OS Independent
Classifier: Programming Language :: Python :: 3
Classifier: Programming Language :: Python :: 3.11
Classifier: Programming Language :: Python :: 3.12
Classifier: Topic :: Software Development :: Libraries :: Python Modules
Classifier: Topic :: Software Development :: Version Control :: Git
Requires-Python: >=3.11
Requires-Dist: httpx>=0.27.0
Requires-Dist: python-dotenv>=1.0.0
Provides-Extra: dev
Requires-Dist: mypy>=1.8.0; extra == 'dev'
Requires-Dist: pytest-asyncio>=0.23.0; extra == 'dev'
Requires-Dist: pytest-mock>=3.12.0; extra == 'dev'
Requires-Dist: pytest>=8.0.0; extra == 'dev'
Requires-Dist: ruff>=0.3.0; extra == 'dev'
Provides-Extra: publish
Requires-Dist: build>=1.0.0; extra == 'publish'
Requires-Dist: twine>=4.0.0; extra == 'publish'
